{
  "hash": "794f869c",
  "configHash": "b502ac6a",
  "lockfileHash": "87b5f6b8",
  "browserHash": "01552574",
  "optimized": {
    "react": {
      "src": "../../node_modules/react/index.js",
      "file": "react.js",
      "fileHash": "09a154c7",
      "needsInterop": true
    },
    "react-dom": {
      "src": "../../node_modules/react-dom/index.js",
      "file": "react-dom.js",
      "fileHash": "c0b67fa6",
      "needsInterop": true
    },
    "zustand": {
      "src": "../../node_modules/zustand/esm/index.mjs",
      "file": "zustand.js",
      "fileHash": "234aab0a",
      "needsInterop": false
    },
    "localforage": {
      "src": "../../node_modules/localforage/dist/localforage.js",
      "file": "localforage.js",
      "fileHash": "a3229703",
      "needsInterop": true
    },
    "date-fns": {
      "src": "../../node_modules/date-fns/esm/index.js",
      "file": "date-fns.js",
      "fileHash": "229b9e59",
      "needsInterop": false
    },
    "lucide-react": {
      "src": "../../node_modules/lucide-react/dist/esm/lucide-react.js",
      "file": "lucide-react.js",
      "fileHash": "eb5948c3",
      "needsInterop": false
    },
    "framer-motion": {
      "src": "../../node_modules/framer-motion/dist/es/index.mjs",
      "file": "framer-motion.js",
      "fileHash": "184b35cd",
      "needsInterop": false
    },
    "jspdf": {
      "src": "../../node_modules/jspdf/dist/jspdf.es.min.js",
      "file": "jspdf.js",
      "fileHash": "1644c709",
      "needsInterop": false
    },
    "html2canvas": {
      "src": "../../node_modules/html2canvas/dist/html2canvas.esm.js",
      "file": "html2canvas.js",
      "fileHash": "f43defc1",
      "needsInterop": false
    },
    "react/jsx-dev-runtime": {
      "src": "../../node_modules/react/jsx-dev-runtime.js",
      "file": "react_jsx-dev-runtime.js",
      "fileHash": "1d642a0a",
      "needsInterop": true
    },
    "react/jsx-runtime": {
      "src": "../../node_modules/react/jsx-runtime.js",
      "file": "react_jsx-runtime.js",
      "fileHash": "95fd76a2",
      "needsInterop": true
    },
    "jspdf-autotable": {
      "src": "../../node_modules/jspdf-autotable/dist/jspdf.plugin.autotable.mjs",
      "file": "jspdf-autotable.js",
      "fileHash": "d198e210",
      "needsInterop": false
    },
    "react-dom/client": {
      "src": "../../node_modules/react-dom/client.js",
      "file": "react-dom_client.js",
      "fileHash": "3bc9caf4",
      "needsInterop": true
    },
    "zustand/middleware": {
      "src": "../../node_modules/zustand/esm/middleware.mjs",
      "file": "zustand_middleware.js",
      "fileHash": "9a2d14be",
      "needsInterop": false
    }
  },
  "chunks": {
    "purify.es-7QLGETF3": {
      "file": "purify__es-7QLGETF3.js"
    },
    "index.es-XWTCVVPM": {
      "file": "index__es-XWTCVVPM.js"
    },
    "chunk-T4IDRJE6": {
      "file": "chunk-T4IDRJE6.js"
    },
    "chunk-XG5IKD4O": {
      "file": "chunk-XG5IKD4O.js"
    },
    "chunk-KL4SNAOQ": {
      "file": "chunk-KL4SNAOQ.js"
    },
    "chunk-ZFPJFB7A": {
      "file": "chunk-ZFPJFB7A.js"
    },
    "chunk-SITVF2AJ": {
      "file": "chunk-SITVF2AJ.js"
    },
    "chunk-PLDDJCW6": {
      "file": "chunk-PLDDJCW6.js"
    }
  }
}